LICENSE
p115qrcode/__init__.py
p115qrcode/__main__.py
p115qrcode/cmd/__init__.py
p115qrcode/cmd/cmd.py
p115qrcode/cmd/init.py
p115qrcode/cmd/web.py
p115qrcode/py.typed
p115qrcode-0.0.5.1.dist-info/LICENSE
p115qrcode-0.0.5.1.dist-info/LICENSE_zh
p115qrcode-0.0.5.1.dist-info/METADATA
p115qrcode-0.0.5.1.dist-info/WHEEL
p115qrcode-0.0.5.1.dist-info/entry_points.txt
p115qrcode-0.0.5.1.dist-info/RECORD
